LICENSE
MANIFEST.in
README.md
setup.cfg
setup.py
pysyncthing/__init__.py
pysyncthing/exceptions.py
pysyncthing/resource.py
pysyncthing/version.py
pysyncthing.egg-info/PKG-INFO
pysyncthing.egg-info/SOURCES.txt
pysyncthing.egg-info/dependency_links.txt
pysyncthing.egg-info/not-zip-safe
pysyncthing.egg-info/requires.txt
pysyncthing.egg-info/top_level.txt