Metadata-Version: 1.0
Name: pysyncthing
Version: 0.0.3
Summary: Python bindings for Syncthing REST API
Home-page: https://github.com/akissa/pysyncthing
Author: Andrew Colin Kissa
Author-email: andrew@topdog.za.net
License: MPL 2.0
Keywords: syncthing sync api rest backup syncronization
Platform: UNKNOWN
Classifier: Development Status :: 3 - Alpha
Classifier: Programming Language :: Python
Classifier: Programming Language :: Python :: 2.6
Classifier: Programming Language :: Python :: 2.7
Classifier: Topic :: Software Development :: Libraries :: Python Modules
Classifier: Intended Audience :: Developers
Classifier: License :: OSI Approved :: Mozilla Public License 2.0 (MPL 2.0)
Classifier: Natural Language :: English
Classifier: Operating System :: OS Independent
